aap/__init__.py
aap/__main__.py
aap/base.py
aap/endpoints.py
aap/mixins.py
python_aap-0.0.12.dist-info/LICENSE
python_aap-0.0.12.dist-info/METADATA
python_aap-0.0.12.dist-info/WHEEL
python_aap-0.0.12.dist-info/entry_points.txt
python_aap-0.0.12.dist-info/top_level.txt
python_aap-0.0.12.dist-info/RECORD
