Metadata-Version: 2.1
Name: python-aap
Version: 0.0.12
Summary: Unofficial python wrapper over Ansible Automation Platform REST API
Author-email: Ivan Mitruk <imitruk@redhat.com>, Marcel Gazdik <mgazdik@redhat.com>
Project-URL: Homepage, https://gitlab.corp.redhat.com/network/python-aap/
Project-URL: Bug Tracker, https://gitlab.corp.redhat.com/network/python-aap/issues
Classifier: Programming Language :: Python :: 3
Classifier: License :: OSI Approved :: GNU General Public License v2 (GPLv2)
Classifier: Operating System :: OS Independent
Requires-Python: >=3.8
License-File: LICENSE
Requires-Dist: requests
Requires-Dist: datetime
